docx2msg/__init__.py
docx2msg/mail_props.py
docx2msg-0.1.2.dist-info/LICENSE
docx2msg-0.1.2.dist-info/METADATA
docx2msg-0.1.2.dist-info/WHEEL
docx2msg-0.1.2.dist-info/top_level.txt
docx2msg-0.1.2.dist-info/RECORD
