Metadata-Version: 2.1
Name: docx2msg
Version: 0.1.2
Summary: Convert a docx to an Outlook Mail-Item.
Author-email: Algebra-FUN <algebra-fun@outlook.com>
License: MIT
Project-URL: Repository, https://github.com/Algebra-FUN/docx2msg
Project-URL: Homepage, https://github.com/Algebra-FUN/docx2msg
Keywords: convert,docx,msg,outlook,mail
Classifier: License :: OSI Approved :: MIT License
Classifier: Programming Language :: Python :: 3
Classifier: Environment :: Win32 (MS Windows)
Classifier: Intended Audience :: Developers
Classifier: Operating System :: Microsoft :: Windows
Requires-Python: >=3.8
License-File: LICENSE
Requires-Dist: pyyaml
Requires-Dist: python-docx
Requires-Dist: docxtpl
Requires-Dist: pywin32
Requires-Dist: beautifulsoup4
